{
  "timestamp": "20250320_140323",
  "total_successful_logins": 50,
  "successful_logins": [
    {
      "type": "Successful Brute Force",
      "severity": "High",
      "url": "http://127.0.0.1:5000/login",
      "method": "POST",
      "username": "system",
      "password": "123456!",
      "parameter": "username, password",
      "payload": "{\"username\": \"system\", \"password\": \"123456!\"}",
      "status_code": 200,
      "response_length": 60,
      "evidence": "Successful login with username: system",
      "details": "Authentication bypass achieved through credential stuffing",
      "recommendation": "1. Implement account lockout after multiple failed attempts\n2. Use strong password policies\n3. Enable multi-factor authentication\n4. Implement rate limiting\n5. Monitor and alert on multiple failed login attempts"
    },
    {
      "type": "Successful Brute Force",
      "severity": "High",
      "url": "http://127.0.0.1:5000/login",
      "method": "POST",
      "username": "user!",
      "password": "Test123!@2023",
      "parameter": "username, password",
      "payload": "{\"username\": \"user!\", \"password\": \"Test123!@2023\"}",
      "status_code": 200,
      "response_length": 60,
      "evidence": "Successful login with username: user!",
      "details": "Authentication bypass achieved through credential stuffing",
      "recommendation": "1. Implement account lockout after multiple failed attempts\n2. Use strong password policies\n3. Enable multi-factor authentication\n4. Implement rate limiting\n5. Monitor and alert on multiple failed login attempts"
    },
    {
      "type": "Successful Brute Force",
      "severity": "High",
      "url": "http://127.0.0.1:5000/login",
      "method": "POST",
      "username": "root_admin",
      "password": "test123!",
      "parameter": "username, password",
      "payload": "{\"username\": \"root_admin\", \"password\": \"test123!\"}",
      "status_code": 200,
      "response_length": 60,
      "evidence": "Successful login with username: root_admin",
      "details": "Authentication bypass achieved through credential stuffing",
      "recommendation": "1. Implement account lockout after multiple failed attempts\n2. Use strong password policies\n3. Enable multi-factor authentication\n4. Implement rate limiting\n5. Monitor and alert on multiple failed login attempts"
    },
    {
      "type": "Successful Brute Force",
      "severity": "High",
      "url": "http://127.0.0.1:5000/login",
      "method": "POST",
      "username": "HELPDESK",
      "password": "123User@2023",
      "parameter": "username, password",
      "payload": "{\"username\": \"HELPDESK\", \"password\": \"123User@2023\"}",
      "status_code": 200,
      "response_length": 60,
      "evidence": "Successful login with username: HELPDESK",
      "details": "Authentication bypass achieved through credential stuffing",
      "recommendation": "1. Implement account lockout after multiple failed attempts\n2. Use strong password policies\n3. Enable multi-factor authentication\n4. Implement rate limiting\n5. Monitor and alert on multiple failed login attempts"
    },
    {
      "type": "Successful Brute Force",
      "severity": "High",
      "url": "http://127.0.0.1:5000/login",
      "method": "POST",
      "username": "postgres",
      "password": "admin",
      "parameter": "username, password",
      "payload": "{\"username\": \"postgres\", \"password\": \"admin\"}",
      "status_code": 200,
      "response_length": 60,
      "evidence": "Successful login with username: postgres",
      "details": "Authentication bypass achieved through credential stuffing",
      "recommendation": "1. Implement account lockout after multiple failed attempts\n2. Use strong password policies\n3. Enable multi-factor authentication\n4. Implement rate limiting\n5. Monitor and alert on multiple failed login attempts"
    },
    {
      "type": "Successful Brute Force",
      "severity": "High",
      "url": "http://127.0.0.1:5000/login",
      "method": "POST",
      "username": "administrator",
      "password": "123admin123",
      "parameter": "username, password",
      "payload": "{\"username\": \"administrator\", \"password\": \"123admin123\"}",
      "status_code": 200,
      "response_length": 60,
      "evidence": "Successful login with username: administrator",
      "details": "Authentication bypass achieved through credential stuffing",
      "recommendation": "1. Implement account lockout after multiple failed attempts\n2. Use strong password policies\n3. Enable multi-factor authentication\n4. Implement rate limiting\n5. Monitor and alert on multiple failed login attempts"
    },
    {
      "type": "Successful Brute Force",
      "severity": "High",
      "url": "http://127.0.0.1:5000/login",
      "method": "POST",
      "username": "guest_admin",
      "password": "test",
      "parameter": "username, password",
      "payload": "{\"username\": \"guest_admin\", \"password\": \"test\"}",
      "status_code": 200,
      "response_length": 60,
      "evidence": "Successful login with username: guest_admin",
      "details": "Authentication bypass achieved through credential stuffing",
      "recommendation": "1. Implement account lockout after multiple failed attempts\n2. Use strong password policies\n3. Enable multi-factor authentication\n4. Implement rate limiting\n5. Monitor and alert on multiple failed login attempts"
    },
    {
      "type": "Successful Brute Force",
      "severity": "High",
      "url": "http://127.0.0.1:5000/login",
      "method": "POST",
      "username": "GUEST",
      "password": "system123",
      "parameter": "username, password",
      "payload": "{\"username\": \"GUEST\", \"password\": \"system123\"}",
      "status_code": 200,
      "response_length": 60,
      "evidence": "Successful login with username: GUEST",
      "details": "Authentication bypass achieved through credential stuffing",
      "recommendation": "1. Implement account lockout after multiple failed attempts\n2. Use strong password policies\n3. Enable multi-factor authentication\n4. Implement rate limiting\n5. Monitor and alert on multiple failed login attempts"
    },
    {
      "type": "Successful Brute Force",
      "severity": "High",
      "url": "http://127.0.0.1:5000/login",
      "method": "POST",
      "username": "support123",
      "password": "123password",
      "parameter": "username, password",
      "payload": "{\"username\": \"support123\", \"password\": \"123password\"}",
      "status_code": 200,
      "response_length": 60,
      "evidence": "Successful login with username: support123",
      "details": "Authentication bypass achieved through credential stuffing",
      "recommendation": "1. Implement account lockout after multiple failed attempts\n2. Use strong password policies\n3. Enable multi-factor authentication\n4. Implement rate limiting\n5. Monitor and alert on multiple failed login attempts"
    },
    {
      "type": "Successful Brute Force",
      "severity": "High",
      "url": "http://127.0.0.1:5000/login",
      "method": "POST",
      "username": "admin!",
      "password": "GUEST",
      "parameter": "username, password",
      "payload": "{\"username\": \"admin!\", \"password\": \"GUEST\"}",
      "status_code": 200,
      "response_length": 60,
      "evidence": "Successful login with username: admin!",
      "details": "Authentication bypass achieved through credential stuffing",
      "recommendation": "1. Implement account lockout after multiple failed attempts\n2. Use strong password policies\n3. Enable multi-factor authentication\n4. Implement rate limiting\n5. Monitor and alert on multiple failed login attempts"
    },
    {
      "type": "Successful Brute Force",
      "severity": "High",
      "url": "http://127.0.0.1:5000/login",
      "method": "POST",
      "username": "administrator123",
      "password": "guest!",
      "parameter": "username, password",
      "payload": "{\"username\": \"administrator123\", \"password\": \"guest!\"}",
      "status_code": 200,
      "response_length": 60,
      "evidence": "Successful login with username: administrator123",
      "details": "Authentication bypass achieved through credential stuffing",
      "recommendation": "1. Implement account lockout after multiple failed attempts\n2. Use strong password policies\n3. Enable multi-factor authentication\n4. Implement rate limiting\n5. Monitor and alert on multiple failed login attempts"
    },
    {
      "type": "Successful Brute Force",
      "severity": "High",
      "url": "http://127.0.0.1:5000/login",
      "method": "POST",
      "username": "mysql!",
      "password": "system123",
      "parameter": "username, password",
      "payload": "{\"username\": \"mysql!\", \"password\": \"system123\"}",
      "status_code": 200,
      "response_length": 60,
      "evidence": "Successful login with username: mysql!",
      "details": "Authentication bypass achieved through credential stuffing",
      "recommendation": "1. Implement account lockout after multiple failed attempts\n2. Use strong password policies\n3. Enable multi-factor authentication\n4. Implement rate limiting\n5. Monitor and alert on multiple failed login attempts"
    },
    {
      "type": "Successful Brute Force",
      "severity": "High",
      "url": "http://127.0.0.1:5000/login",
      "method": "POST",
      "username": "root!",
      "password": "123Help@desk",
      "parameter": "username, password",
      "payload": "{\"username\": \"root!\", \"password\": \"123Help@desk\"}",
      "status_code": 200,
      "response_length": 60,
      "evidence": "Successful login with username: root!",
      "details": "Authentication bypass achieved through credential stuffing",
      "recommendation": "1. Implement account lockout after multiple failed attempts\n2. Use strong password policies\n3. Enable multi-factor authentication\n4. Implement rate limiting\n5. Monitor and alert on multiple failed login attempts"
    },
    {
      "type": "Successful Brute Force",
      "severity": "High",
      "url": "http://127.0.0.1:5000/login",
      "method": "POST",
      "username": "test123",
      "password": "user@2023",
      "parameter": "username, password",
      "payload": "{\"username\": \"test123\", \"password\": \"user@2023\"}",
      "status_code": 200,
      "response_length": 60,
      "evidence": "Successful login with username: test123",
      "details": "Authentication bypass achieved through credential stuffing",
      "recommendation": "1. Implement account lockout after multiple failed attempts\n2. Use strong password policies\n3. Enable multi-factor authentication\n4. Implement rate limiting\n5. Monitor and alert on multiple failed login attempts"
    },
    {
      "type": "Successful Brute Force",
      "severity": "High",
      "url": "http://127.0.0.1:5000/login",
      "method": "POST",
      "username": "support123",
      "password": "mysql",
      "parameter": "username, password",
      "payload": "{\"username\": \"support123\", \"password\": \"mysql\"}",
      "status_code": 200,
      "response_length": 60,
      "evidence": "Successful login with username: support123",
      "details": "Authentication bypass achieved through credential stuffing",
      "recommendation": "1. Implement account lockout after multiple failed attempts\n2. Use strong password policies\n3. Enable multi-factor authentication\n4. Implement rate limiting\n5. Monitor and alert on multiple failed login attempts"
    },
    {
      "type": "Successful Brute Force",
      "severity": "High",
      "url": "http://127.0.0.1:5000/login",
      "method": "POST",
      "username": "support!",
      "password": "admin",
      "parameter": "username, password",
      "payload": "{\"username\": \"support!\", \"password\": \"admin\"}",
      "status_code": 200,
      "response_length": 60,
      "evidence": "Successful login with username: support!",
      "details": "Authentication bypass achieved through credential stuffing",
      "recommendation": "1. Implement account lockout after multiple failed attempts\n2. Use strong password policies\n3. Enable multi-factor authentication\n4. Implement rate limiting\n5. Monitor and alert on multiple failed login attempts"
    },
    {
      "type": "Successful Brute Force",
      "severity": "High",
      "url": "http://127.0.0.1:5000/login",
      "method": "POST",
      "username": "mysql",
      "password": "ADMIN@123",
      "parameter": "username, password",
      "payload": "{\"username\": \"mysql\", \"password\": \"ADMIN@123\"}",
      "status_code": 200,
      "response_length": 60,
      "evidence": "Successful login with username: mysql",
      "details": "Authentication bypass achieved through credential stuffing",
      "recommendation": "1. Implement account lockout after multiple failed attempts\n2. Use strong password policies\n3. Enable multi-factor authentication\n4. Implement rate limiting\n5. Monitor and alert on multiple failed login attempts"
    },
    {
      "type": "Successful Brute Force",
      "severity": "High",
      "url": "http://127.0.0.1:5000/login",
      "method": "POST",
      "username": "guest_user",
      "password": "Support2023123",
      "parameter": "username, password",
      "payload": "{\"username\": \"guest_user\", \"password\": \"Support2023123\"}",
      "status_code": 200,
      "response_length": 60,
      "evidence": "Successful login with username: guest_user",
      "details": "Authentication bypass achieved through credential stuffing",
      "recommendation": "1. Implement account lockout after multiple failed attempts\n2. Use strong password policies\n3. Enable multi-factor authentication\n4. Implement rate limiting\n5. Monitor and alert on multiple failed login attempts"
    },
    {
      "type": "Successful Brute Force",
      "severity": "High",
      "url": "http://127.0.0.1:5000/login",
      "method": "POST",
      "username": "root_admin",
      "password": "123admin@123",
      "parameter": "username, password",
      "payload": "{\"username\": \"root_admin\", \"password\": \"123admin@123\"}",
      "status_code": 200,
      "response_length": 60,
      "evidence": "Successful login with username: root_admin",
      "details": "Authentication bypass achieved through credential stuffing",
      "recommendation": "1. Implement account lockout after multiple failed attempts\n2. Use strong password policies\n3. Enable multi-factor authentication\n4. Implement rate limiting\n5. Monitor and alert on multiple failed login attempts"
    },
    {
      "type": "Successful Brute Force",
      "severity": "High",
      "url": "http://127.0.0.1:5000/login",
      "method": "POST",
      "username": "mysql_user",
      "password": "123system",
      "parameter": "username, password",
      "payload": "{\"username\": \"mysql_user\", \"password\": \"123system\"}",
      "status_code": 200,
      "response_length": 60,
      "evidence": "Successful login with username: mysql_user",
      "details": "Authentication bypass achieved through credential stuffing",
      "recommendation": "1. Implement account lockout after multiple failed attempts\n2. Use strong password policies\n3. Enable multi-factor authentication\n4. Implement rate limiting\n5. Monitor and alert on multiple failed login attempts"
    },
    {
      "type": "Successful Brute Force",
      "severity": "High",
      "url": "http://127.0.0.1:5000/login",
      "method": "POST",
      "username": "ADMINISTRATOR",
      "password": "GUEST",
      "parameter": "username, password",
      "payload": "{\"username\": \"ADMINISTRATOR\", \"password\": \"GUEST\"}",
      "status_code": 200,
      "response_length": 60,
      "evidence": "Successful login with username: ADMINISTRATOR",
      "details": "Authentication bypass achieved through credential stuffing",
      "recommendation": "1. Implement account lockout after multiple failed attempts\n2. Use strong password policies\n3. Enable multi-factor authentication\n4. Implement rate limiting\n5. Monitor and alert on multiple failed login attempts"
    },
    {
      "type": "Successful Brute Force",
      "severity": "High",
      "url": "http://127.0.0.1:5000/login",
      "method": "POST",
      "username": "SUPPORT",
      "password": "123test",
      "parameter": "username, password",
      "payload": "{\"username\": \"SUPPORT\", \"password\": \"123test\"}",
      "status_code": 200,
      "response_length": 60,
      "evidence": "Successful login with username: SUPPORT",
      "details": "Authentication bypass achieved through credential stuffing",
      "recommendation": "1. Implement account lockout after multiple failed attempts\n2. Use strong password policies\n3. Enable multi-factor authentication\n4. Implement rate limiting\n5. Monitor and alert on multiple failed login attempts"
    },
    {
      "type": "Successful Brute Force",
      "severity": "High",
      "url": "http://127.0.0.1:5000/login",
      "method": "POST",
      "username": "POSTGRES",
      "password": "admin123!",
      "parameter": "username, password",
      "payload": "{\"username\": \"POSTGRES\", \"password\": \"admin123!\"}",
      "status_code": 200,
      "response_length": 60,
      "evidence": "Successful login with username: POSTGRES",
      "details": "Authentication bypass achieved through credential stuffing",
      "recommendation": "1. Implement account lockout after multiple failed attempts\n2. Use strong password policies\n3. Enable multi-factor authentication\n4. Implement rate limiting\n5. Monitor and alert on multiple failed login attempts"
    },
    {
      "type": "Successful Brute Force",
      "severity": "High",
      "url": "http://127.0.0.1:5000/login",
      "method": "POST",
      "username": "support!",
      "password": "123password",
      "parameter": "username, password",
      "payload": "{\"username\": \"support!\", \"password\": \"123password\"}",
      "status_code": 200,
      "response_length": 60,
      "evidence": "Successful login with username: support!",
      "details": "Authentication bypass achieved through credential stuffing",
      "recommendation": "1. Implement account lockout after multiple failed attempts\n2. Use strong password policies\n3. Enable multi-factor authentication\n4. Implement rate limiting\n5. Monitor and alert on multiple failed login attempts"
    },
    {
      "type": "Successful Brute Force",
      "severity": "High",
      "url": "http://127.0.0.1:5000/login",
      "method": "POST",
      "username": "helpdesk",
      "password": "123123456",
      "parameter": "username, password",
      "payload": "{\"username\": \"helpdesk\", \"password\": \"123123456\"}",
      "status_code": 200,
      "response_length": 60,
      "evidence": "Successful login with username: helpdesk",
      "details": "Authentication bypass achieved through credential stuffing",
      "recommendation": "1. Implement account lockout after multiple failed attempts\n2. Use strong password policies\n3. Enable multi-factor authentication\n4. Implement rate limiting\n5. Monitor and alert on multiple failed login attempts"
    },
    {
      "type": "Successful Brute Force",
      "severity": "High",
      "url": "http://127.0.0.1:5000/login",
      "method": "POST",
      "username": "USER",
      "password": "Help@desk@2023",
      "parameter": "username, password",
      "payload": "{\"username\": \"USER\", \"password\": \"Help@desk@2023\"}",
      "status_code": 200,
      "response_length": 60,
      "evidence": "Successful login with username: USER",
      "details": "Authentication bypass achieved through credential stuffing",
      "recommendation": "1. Implement account lockout after multiple failed attempts\n2. Use strong password policies\n3. Enable multi-factor authentication\n4. Implement rate limiting\n5. Monitor and alert on multiple failed login attempts"
    },
    {
      "type": "Successful Brute Force",
      "severity": "High",
      "url": "http://127.0.0.1:5000/login",
      "method": "POST",
      "username": "test_user",
      "password": "123test",
      "parameter": "username, password",
      "payload": "{\"username\": \"test_user\", \"password\": \"123test\"}",
      "status_code": 200,
      "response_length": 60,
      "evidence": "Successful login with username: test_user",
      "details": "Authentication bypass achieved through credential stuffing",
      "recommendation": "1. Implement account lockout after multiple failed attempts\n2. Use strong password policies\n3. Enable multi-factor authentication\n4. Implement rate limiting\n5. Monitor and alert on multiple failed login attempts"
    },
    {
      "type": "Successful Brute Force",
      "severity": "High",
      "url": "http://127.0.0.1:5000/login",
      "method": "POST",
      "username": "guest123",
      "password": "123User@2023",
      "parameter": "username, password",
      "payload": "{\"username\": \"guest123\", \"password\": \"123User@2023\"}",
      "status_code": 200,
      "response_length": 60,
      "evidence": "Successful login with username: guest123",
      "details": "Authentication bypass achieved through credential stuffing",
      "recommendation": "1. Implement account lockout after multiple failed attempts\n2. Use strong password policies\n3. Enable multi-factor authentication\n4. Implement rate limiting\n5. Monitor and alert on multiple failed login attempts"
    },
    {
      "type": "Successful Brute Force",
      "severity": "High",
      "url": "http://127.0.0.1:5000/login",
      "method": "POST",
      "username": "mysql123",
      "password": "root!",
      "parameter": "username, password",
      "payload": "{\"username\": \"mysql123\", \"password\": \"root!\"}",
      "status_code": 200,
      "response_length": 60,
      "evidence": "Successful login with username: mysql123",
      "details": "Authentication bypass achieved through credential stuffing",
      "recommendation": "1. Implement account lockout after multiple failed attempts\n2. Use strong password policies\n3. Enable multi-factor authentication\n4. Implement rate limiting\n5. Monitor and alert on multiple failed login attempts"
    },
    {
      "type": "Successful Brute Force",
      "severity": "High",
      "url": "http://127.0.0.1:5000/login",
      "method": "POST",
      "username": "support",
      "password": "POSTGRES",
      "parameter": "username, password",
      "payload": "{\"username\": \"support\", \"password\": \"POSTGRES\"}",
      "status_code": 200,
      "response_length": 60,
      "evidence": "Successful login with username: support",
      "details": "Authentication bypass achieved through credential stuffing",
      "recommendation": "1. Implement account lockout after multiple failed attempts\n2. Use strong password policies\n3. Enable multi-factor authentication\n4. Implement rate limiting\n5. Monitor and alert on multiple failed login attempts"
    },
    {
      "type": "Successful Brute Force",
      "severity": "High",
      "url": "http://127.0.0.1:5000/login",
      "method": "POST",
      "username": "admin123",
      "password": "PASSWORD123",
      "parameter": "username, password",
      "payload": "{\"username\": \"admin123\", \"password\": \"PASSWORD123\"}",
      "status_code": 200,
      "response_length": 60,
      "evidence": "Successful login with username: admin123",
      "details": "Authentication bypass achieved through credential stuffing",
      "recommendation": "1. Implement account lockout after multiple failed attempts\n2. Use strong password policies\n3. Enable multi-factor authentication\n4. Implement rate limiting\n5. Monitor and alert on multiple failed login attempts"
    },
    {
      "type": "Successful Brute Force",
      "severity": "High",
      "url": "http://127.0.0.1:5000/login",
      "method": "POST",
      "username": "support_admin",
      "password": "admin123",
      "parameter": "username, password",
      "payload": "{\"username\": \"support_admin\", \"password\": \"admin123\"}",
      "status_code": 200,
      "response_length": 60,
      "evidence": "Successful login with username: support_admin",
      "details": "Authentication bypass achieved through credential stuffing",
      "recommendation": "1. Implement account lockout after multiple failed attempts\n2. Use strong password policies\n3. Enable multi-factor authentication\n4. Implement rate limiting\n5. Monitor and alert on multiple failed login attempts"
    },
    {
      "type": "Successful Brute Force",
      "severity": "High",
      "url": "http://127.0.0.1:5000/login",
      "method": "POST",
      "username": "root!",
      "password": "Support2023123",
      "parameter": "username, password",
      "payload": "{\"username\": \"root!\", \"password\": \"Support2023123\"}",
      "status_code": 200,
      "response_length": 60,
      "evidence": "Successful login with username: root!",
      "details": "Authentication bypass achieved through credential stuffing",
      "recommendation": "1. Implement account lockout after multiple failed attempts\n2. Use strong password policies\n3. Enable multi-factor authentication\n4. Implement rate limiting\n5. Monitor and alert on multiple failed login attempts"
    },
    {
      "type": "Successful Brute Force",
      "severity": "High",
      "url": "http://127.0.0.1:5000/login",
      "method": "POST",
      "username": "admin",
      "password": "password123123",
      "parameter": "username, password",
      "payload": "{\"username\": \"admin\", \"password\": \"password123123\"}",
      "status_code": 200,
      "response_length": 60,
      "evidence": "Successful login with username: admin",
      "details": "Authentication bypass achieved through credential stuffing",
      "recommendation": "1. Implement account lockout after multiple failed attempts\n2. Use strong password policies\n3. Enable multi-factor authentication\n4. Implement rate limiting\n5. Monitor and alert on multiple failed login attempts"
    },
    {
      "type": "Successful Brute Force",
      "severity": "High",
      "url": "http://127.0.0.1:5000/login",
      "method": "POST",
      "username": "mysql_user",
      "password": "password",
      "parameter": "username, password",
      "payload": "{\"username\": \"mysql_user\", \"password\": \"password\"}",
      "status_code": 200,
      "response_length": 60,
      "evidence": "Successful login with username: mysql_user",
      "details": "Authentication bypass achieved through credential stuffing",
      "recommendation": "1. Implement account lockout after multiple failed attempts\n2. Use strong password policies\n3. Enable multi-factor authentication\n4. Implement rate limiting\n5. Monitor and alert on multiple failed login attempts"
    },
    {
      "type": "Successful Brute Force",
      "severity": "High",
      "url": "http://127.0.0.1:5000/login",
      "method": "POST",
      "username": "helpdesk_admin",
      "password": "Support2023@2023",
      "parameter": "username, password",
      "payload": "{\"username\": \"helpdesk_admin\", \"password\": \"Support2023@2023\"}",
      "status_code": 200,
      "response_length": 60,
      "evidence": "Successful login with username: helpdesk_admin",
      "details": "Authentication bypass achieved through credential stuffing",
      "recommendation": "1. Implement account lockout after multiple failed attempts\n2. Use strong password policies\n3. Enable multi-factor authentication\n4. Implement rate limiting\n5. Monitor and alert on multiple failed login attempts"
    },
    {
      "type": "Successful Brute Force",
      "severity": "High",
      "url": "http://127.0.0.1:5000/login",
      "method": "POST",
      "username": "support!",
      "password": "Test123!!",
      "parameter": "username, password",
      "payload": "{\"username\": \"support!\", \"password\": \"Test123!!\"}",
      "status_code": 200,
      "response_length": 60,
      "evidence": "Successful login with username: support!",
      "details": "Authentication bypass achieved through credential stuffing",
      "recommendation": "1. Implement account lockout after multiple failed attempts\n2. Use strong password policies\n3. Enable multi-factor authentication\n4. Implement rate limiting\n5. Monitor and alert on multiple failed login attempts"
    },
    {
      "type": "Successful Brute Force",
      "severity": "High",
      "url": "http://127.0.0.1:5000/login",
      "method": "POST",
      "username": "postgres",
      "password": "guest123",
      "parameter": "username, password",
      "payload": "{\"username\": \"postgres\", \"password\": \"guest123\"}",
      "status_code": 200,
      "response_length": 60,
      "evidence": "Successful login with username: postgres",
      "details": "Authentication bypass achieved through credential stuffing",
      "recommendation": "1. Implement account lockout after multiple failed attempts\n2. Use strong password policies\n3. Enable multi-factor authentication\n4. Implement rate limiting\n5. Monitor and alert on multiple failed login attempts"
    },
    {
      "type": "Successful Brute Force",
      "severity": "High",
      "url": "http://127.0.0.1:5000/login",
      "method": "POST",
      "username": "guest_user",
      "password": "help@desk",
      "parameter": "username, password",
      "payload": "{\"username\": \"guest_user\", \"password\": \"help@desk\"}",
      "status_code": 200,
      "response_length": 60,
      "evidence": "Successful login with username: guest_user",
      "details": "Authentication bypass achieved through credential stuffing",
      "recommendation": "1. Implement account lockout after multiple failed attempts\n2. Use strong password policies\n3. Enable multi-factor authentication\n4. Implement rate limiting\n5. Monitor and alert on multiple failed login attempts"
    },
    {
      "type": "Successful Brute Force",
      "severity": "High",
      "url": "http://127.0.0.1:5000/login",
      "method": "POST",
      "username": "user",
      "password": "postgres",
      "parameter": "username, password",
      "payload": "{\"username\": \"user\", \"password\": \"postgres\"}",
      "status_code": 200,
      "response_length": 60,
      "evidence": "Successful login with username: user",
      "details": "Authentication bypass achieved through credential stuffing",
      "recommendation": "1. Implement account lockout after multiple failed attempts\n2. Use strong password policies\n3. Enable multi-factor authentication\n4. Implement rate limiting\n5. Monitor and alert on multiple failed login attempts"
    },
    {
      "type": "Successful Brute Force",
      "severity": "High",
      "url": "http://127.0.0.1:5000/login",
      "method": "POST",
      "username": "admin123",
      "password": "123456@2023",
      "parameter": "username, password",
      "payload": "{\"username\": \"admin123\", \"password\": \"123456@2023\"}",
      "status_code": 200,
      "response_length": 60,
      "evidence": "Successful login with username: admin123",
      "details": "Authentication bypass achieved through credential stuffing",
      "recommendation": "1. Implement account lockout after multiple failed attempts\n2. Use strong password policies\n3. Enable multi-factor authentication\n4. Implement rate limiting\n5. Monitor and alert on multiple failed login attempts"
    },
    {
      "type": "Successful Brute Force",
      "severity": "High",
      "url": "http://127.0.0.1:5000/login",
      "method": "POST",
      "username": "postgres_user",
      "password": "postgres123",
      "parameter": "username, password",
      "payload": "{\"username\": \"postgres_user\", \"password\": \"postgres123\"}",
      "status_code": 200,
      "response_length": 60,
      "evidence": "Successful login with username: postgres_user",
      "details": "Authentication bypass achieved through credential stuffing",
      "recommendation": "1. Implement account lockout after multiple failed attempts\n2. Use strong password policies\n3. Enable multi-factor authentication\n4. Implement rate limiting\n5. Monitor and alert on multiple failed login attempts"
    },
    {
      "type": "Successful Brute Force",
      "severity": "High",
      "url": "http://127.0.0.1:5000/login",
      "method": "POST",
      "username": "administrator",
      "password": "123password",
      "parameter": "username, password",
      "payload": "{\"username\": \"administrator\", \"password\": \"123password\"}",
      "status_code": 200,
      "response_length": 60,
      "evidence": "Successful login with username: administrator",
      "details": "Authentication bypass achieved through credential stuffing",
      "recommendation": "1. Implement account lockout after multiple failed attempts\n2. Use strong password policies\n3. Enable multi-factor authentication\n4. Implement rate limiting\n5. Monitor and alert on multiple failed login attempts"
    },
    {
      "type": "Successful Brute Force",
      "severity": "High",
      "url": "http://127.0.0.1:5000/login",
      "method": "POST",
      "username": "admin",
      "password": "postgres123",
      "parameter": "username, password",
      "payload": "{\"username\": \"admin\", \"password\": \"postgres123\"}",
      "status_code": 200,
      "response_length": 60,
      "evidence": "Successful login with username: admin",
      "details": "Authentication bypass achieved through credential stuffing",
      "recommendation": "1. Implement account lockout after multiple failed attempts\n2. Use strong password policies\n3. Enable multi-factor authentication\n4. Implement rate limiting\n5. Monitor and alert on multiple failed login attempts"
    },
    {
      "type": "Successful Brute Force",
      "severity": "High",
      "url": "http://127.0.0.1:5000/login",
      "method": "POST",
      "username": "admin!",
      "password": "root",
      "parameter": "username, password",
      "payload": "{\"username\": \"admin!\", \"password\": \"root\"}",
      "status_code": 200,
      "response_length": 60,
      "evidence": "Successful login with username: admin!",
      "details": "Authentication bypass achieved through credential stuffing",
      "recommendation": "1. Implement account lockout after multiple failed attempts\n2. Use strong password policies\n3. Enable multi-factor authentication\n4. Implement rate limiting\n5. Monitor and alert on multiple failed login attempts"
    },
    {
      "type": "Successful Brute Force",
      "severity": "High",
      "url": "http://127.0.0.1:5000/login",
      "method": "POST",
      "username": "ROOT",
      "password": "root",
      "parameter": "username, password",
      "payload": "{\"username\": \"ROOT\", \"password\": \"root\"}",
      "status_code": 200,
      "response_length": 60,
      "evidence": "Successful login with username: ROOT",
      "details": "Authentication bypass achieved through credential stuffing",
      "recommendation": "1. Implement account lockout after multiple failed attempts\n2. Use strong password policies\n3. Enable multi-factor authentication\n4. Implement rate limiting\n5. Monitor and alert on multiple failed login attempts"
    },
    {
      "type": "Successful Brute Force",
      "severity": "High",
      "url": "http://127.0.0.1:5000/login",
      "method": "POST",
      "username": "root!",
      "password": "password",
      "parameter": "username, password",
      "payload": "{\"username\": \"root!\", \"password\": \"password\"}",
      "status_code": 200,
      "response_length": 60,
      "evidence": "Successful login with username: root!",
      "details": "Authentication bypass achieved through credential stuffing",
      "recommendation": "1. Implement account lockout after multiple failed attempts\n2. Use strong password policies\n3. Enable multi-factor authentication\n4. Implement rate limiting\n5. Monitor and alert on multiple failed login attempts"
    },
    {
      "type": "Successful Brute Force",
      "severity": "High",
      "url": "http://127.0.0.1:5000/login",
      "method": "POST",
      "username": "mysql_user",
      "password": "Password123!!",
      "parameter": "username, password",
      "payload": "{\"username\": \"mysql_user\", \"password\": \"Password123!!\"}",
      "status_code": 200,
      "response_length": 60,
      "evidence": "Successful login with username: mysql_user",
      "details": "Authentication bypass achieved through credential stuffing",
      "recommendation": "1. Implement account lockout after multiple failed attempts\n2. Use strong password policies\n3. Enable multi-factor authentication\n4. Implement rate limiting\n5. Monitor and alert on multiple failed login attempts"
    },
    {
      "type": "Successful Brute Force",
      "severity": "High",
      "url": "http://127.0.0.1:5000/login",
      "method": "POST",
      "username": "guest_admin",
      "password": "123test",
      "parameter": "username, password",
      "payload": "{\"username\": \"guest_admin\", \"password\": \"123test\"}",
      "status_code": 200,
      "response_length": 60,
      "evidence": "Successful login with username: guest_admin",
      "details": "Authentication bypass achieved through credential stuffing",
      "recommendation": "1. Implement account lockout after multiple failed attempts\n2. Use strong password policies\n3. Enable multi-factor authentication\n4. Implement rate limiting\n5. Monitor and alert on multiple failed login attempts"
    },
    {
      "type": "Successful Brute Force",
      "severity": "High",
      "url": "http://127.0.0.1:5000/login",
      "method": "POST",
      "username": "administrator_admin",
      "password": "123guest",
      "parameter": "username, password",
      "payload": "{\"username\": \"administrator_admin\", \"password\": \"123guest\"}",
      "status_code": 200,
      "response_length": 60,
      "evidence": "Successful login with username: administrator_admin",
      "details": "Authentication bypass achieved through credential stuffing",
      "recommendation": "1. Implement account lockout after multiple failed attempts\n2. Use strong password policies\n3. Enable multi-factor authentication\n4. Implement rate limiting\n5. Monitor and alert on multiple failed login attempts"
    }
  ]
}